{
    "qualityModel": false,
    "transactionsConfiguration": false,
    "name": "com.castsoftware.dotnet.ado",
    "href": "AIP/extensions/com.castsoftware.dotnet.ado",
    "title": "ADO for .NET",
    "description": "This extension supports ADO.NET.",
    "iconUrl": "https://raw.githubusercontent.com/CAST-Extend/resources/master/com.castsoftware.adonet.png",
    "versions": {
        "name": "versions from latest to oldest",
        "href": "AIP/extensions/com.castsoftware.dotnet.ado/versions"
    }
}
