{
    "qualityModel": false,
    "transactionsConfiguration": false,
    "name": "com.castsoftware.java.sql",
    "href": "AIP/extensions/com.castsoftware.java.sql",
    "title": "JDBC",
    "description": "This extension supports API for all the JDBC packages which is responsible for the typical CRUD operations with the database.",
    "iconUrl": "https://raw.githubusercontent.com/CAST-Extend/resources/master/com.castsoftware.java.sql.png",
    "versions": {
        "name": "versions from latest to oldest",
        "href": "AIP/extensions/com.castsoftware.java.sql/versions"
    }
}
