[
    {
        "id": 1200070,
        "name": "Using Cloud IAM (Identity & Access Management) for managing specific resources access authorization",
        "href": "HL/cloud-ready/detection-patterns/1200070"
    },
    {
        "id": 1200117,
        "name": "Using Cloud-based database services",
        "href": "HL/cloud-ready/detection-patterns/1200117"
    },
    {
        "id": 1200102,
        "name": "Using Devops automation and IaC (Infrastructure as Code)",
        "href": "HL/cloud-ready/detection-patterns/1200102"
    },
    {
        "id": 1200103,
        "name": "Using ETLs (Extract Transform Load)",
        "href": "HL/cloud-ready/detection-patterns/1200103"
    },
    {
        "id": 1200107,
        "name": "Using Monitoring Service",
        "href": "HL/cloud-ready/detection-patterns/1200107"
    },
    {
        "id": 1200110,
        "name": "Using NoSQL document storage",
        "href": "HL/cloud-ready/detection-patterns/1200110"
    },
    {
        "id": 1200067,
        "name": "Using a Cloud-based Access Control",
        "href": "HL/cloud-ready/detection-patterns/1200067"
    },
    {
        "id": 1200068,
        "name": "Using a Cloud-based Active Directory",
        "href": "HL/cloud-ready/detection-patterns/1200068"
    },
    {
        "id": 1200095,
        "name": "Using a Cloud-based Batch Job Orchestration",
        "href": "HL/cloud-ready/detection-patterns/1200095"
    },
    {
        "id": 1200096,
        "name": "Using a Cloud-based Big Data technology (EMR)",
        "href": "HL/cloud-ready/detection-patterns/1200096"
    },
    {
        "id": 1200086,
        "name": "Using a Cloud-based Service Bus",
        "href": "HL/cloud-ready/detection-patterns/1200086"
    },
    {
        "id": 1200082,
        "name": "Using a Cloud-based cache Management Framework",
        "href": "HL/cloud-ready/detection-patterns/1200082"
    },
    {
        "id": 1200118,
        "name": "Using a Cloud-based container service",
        "href": "HL/cloud-ready/detection-patterns/1200118"
    },
    {
        "id": 1200087,
        "name": "Using a Cloud-based data storage",
        "href": "HL/cloud-ready/detection-patterns/1200087"
    },
    {
        "id": 1200094,
        "name": "Using a Cloud-based function as a service (Serverless)",
        "href": "HL/cloud-ready/detection-patterns/1200094"
    },
    {
        "id": 1200084,
        "name": "Using a Cloud-based key storage",
        "href": "HL/cloud-ready/detection-patterns/1200084"
    },
    {
        "id": 1200119,
        "name": "Using a Cloud-based search engine",
        "href": "HL/cloud-ready/detection-patterns/1200119"
    },
    {
        "id": 1200099,
        "name": "Using a Cloud-based task scheduling service",
        "href": "HL/cloud-ready/detection-patterns/1200099"
    },
    {
        "id": 1200106,
        "name": "Using a Load Balancer",
        "href": "HL/cloud-ready/detection-patterns/1200106"
    },
    {
        "id": 1200089,
        "name": "Using cloud specific storage component",
        "href": "HL/cloud-ready/detection-patterns/1200089"
    }
]
