{
    "id": 1200092,
    "name": "Using PostgreSQL database",
    "href": "HL/cloud-ready/detection-patterns/1200092",
    "contribution": {
        "href": "HL/cloud-ready/contributions/2",
        "name": "Booster"
    },
    "category": {
        "href": "HL/cloud-ready/categories/7",
        "name": "Execution Environment"
    },
    "scope": [
        {
            "platform": {
                "href": "HL/cloud-ready/platforms/0",
                "name": "Agnostic"
            },
            "technology": {
                "href": "HL/cloud-ready/technologies/6",
                "name": "PHP"
            }
        },
        {
            "platform": {
                "href": "HL/cloud-ready/platforms/0",
                "name": "Agnostic"
            },
            "technology": {
                "href": "HL/cloud-ready/technologies/8",
                "name": "SWIFT"
            }
        },
        {
            "platform": {
                "href": "HL/cloud-ready/platforms/0",
                "name": "Agnostic"
            },
            "technology": {
                "href": "HL/cloud-ready/technologies/4",
                "name": "JavaScript"
            }
        },
        {
            "platform": {
                "href": "HL/cloud-ready/platforms/0",
                "name": "Agnostic"
            },
            "technology": {
                "href": "HL/cloud-ready/technologies/13",
                "name": "Scala"
            }
        },
        {
            "platform": {
                "href": "HL/cloud-ready/platforms/0",
                "name": "Agnostic"
            },
            "technology": {
                "href": "HL/cloud-ready/technologies/14",
                "name": "Clojure"
            }
        },
        {
            "platform": {
                "href": "HL/cloud-ready/platforms/0",
                "name": "Agnostic"
            },
            "technology": {
                "href": "HL/cloud-ready/technologies/5",
                "name": "Kotlin"
            }
        },
        {
            "platform": {
                "href": "HL/cloud-ready/platforms/0",
                "name": "Agnostic"
            },
            "technology": {
                "href": "HL/cloud-ready/technologies/3",
                "name": "Java"
            }
        },
        {
            "platform": {
                "href": "HL/cloud-ready/platforms/0",
                "name": "Agnostic"
            },
            "technology": {
                "href": "HL/cloud-ready/technologies/1",
                "name": "C#"
            }
        },
        {
            "platform": {
                "href": "HL/cloud-ready/platforms/0",
                "name": "Agnostic"
            },
            "technology": {
                "href": "HL/cloud-ready/technologies/11",
                "name": "VB/VB.Net"
            }
        },
        {
            "platform": {
                "href": "HL/cloud-ready/platforms/0",
                "name": "Agnostic"
            },
            "technology": {
                "href": "HL/cloud-ready/technologies/7",
                "name": "Python"
            }
        },
        {
            "platform": {
                "href": "HL/cloud-ready/platforms/0",
                "name": "Agnostic"
            },
            "technology": {
                "href": "HL/cloud-ready/technologies/10",
                "name": "TypeScript"
            }
        }
    ],
    "platformMigration": {
        "criticality": {
            "href": "HL/cloud-ready/criticality/10",
            "name": "Low"
        },
        "description": "This CloudReady pattern detects in the source code the usage of a PostgreSQL database. PostgreSQL is available as a service in the majority of Cloud/PaaS platforms, providing your application with native high scalability, elasticity and availability.",
        "migrationImpacts": [
            {
                "href": "HL/cloud-ready/migration-impacts/0",
                "name": "None"
            }
        ],
        "reference": "AWS: https://aws.amazon.com/rds/postgresql/\nMicrosoft Azure: https://azure.microsoft.com/en-us/services/postgresql/\nGoogle CloudPlatform: https://cloud.google.com/sql/docs/postgres/"
    }
}
